LICENSE
pysapphire/__init__.py
pysapphire/sapphire.py
pysapphire-0.1.1.dist-info/LICENSE
pysapphire-0.1.1.dist-info/WHEEL
pysapphire-0.1.1.dist-info/METADATA
pysapphire-0.1.1.dist-info/RECORD
