Metadata-Version: 2.1
Name: pysapphire
Version: 0.1.1
Summary: Python implementation of the Sapphire II Stream Cipher Algorithm
Home-page: https://github.com/Gigahawk/pysapphire
License: LGPL-2.1-or-later
Keywords: sapphire,cipher
Author: Jasper Chan
Author-email: jasperchan515@gmail.com
Requires-Python: >=3.6,<4.0
Classifier: License :: OSI Approved
Classifier: Programming Language :: Python :: 3
Classifier: Programming Language :: Python :: 3.6
Classifier: Programming Language :: Python :: 3.7
Classifier: Programming Language :: Python :: 3.8
Project-URL: Repository, https://github.com/Gigahawk/pysapphire
